variation_number/__init__.py
variation_number/vn.py
variation_number-0.2.5.dist-info/METADATA
variation_number-0.2.5.dist-info/WHEEL
variation_number-0.2.5.dist-info/licenses/LICENSE
variation_number-0.2.5.dist-info/RECORD
