Metadata-Version: 2.1
Name: variation_number
Version: 0.2.5
Summary: A package for computing variation numbers
Project-URL: Homepage, https://github.com/jiaying2508/variation_number
Author-email: Jiaying Lai <jiaying_lai@brown.edu>
License: Copyright (c) 2022, Jiaying Lai
License-File: LICENSE
Classifier: License :: OSI Approved :: MIT License
Classifier: Operating System :: OS Independent
Classifier: Programming Language :: Python :: 3
Requires-Python: >=3.7
